version.txt
filepilot/__init__.py
filepilot/__main__.py
filepilot/changemanager.py
filepilot/claude.py
filepilot/filepilot.py
filepilot/syntaxdiff.py
filepilot/cli/__init__.py
filepilot/cli/analyze.py
filepilot/cli/change.py
filepilot/cli/changedir.py
filepilot/cli/create.py
filepilot/cli/createdir.py
filepilot/cli/status.py
filepilot/cli/update.py
filepilot-0.5.0.dist-info/LICENSE
filepilot-0.5.0.dist-info/METADATA
filepilot-0.5.0.dist-info/WHEEL
filepilot-0.5.0.dist-info/entry_points.txt
filepilot-0.5.0.dist-info/top_level.txt
filepilot-0.5.0.dist-info/RECORD
