Metadata-Version: 2.1
Name: filepilot
Version: 0.5.0
Summary: AI-powered tool for creating, analyzing, and modifying files using natural language
Home-page: https://github.com/joaompinto/filepilot
Author: João Pinto
Project-URL: Source, https://github.com/joaompinto/filepilot
Project-URL: Bug Tracker, https://github.com/joaompinto/filepilot/issues
Classifier: Development Status :: 3 - Alpha
Classifier: Environment :: Console
Classifier: Intended Audience :: Developers
Classifier: License :: OSI Approved :: MIT License
Classifier: Programming Language :: Python :: 3
Classifier: Programming Language :: Python :: 3.8
Classifier: Programming Language :: Python :: 3.9
Classifier: Programming Language :: Python :: 3.10
Classifier: Programming Language :: Python :: 3.11
Classifier: Topic :: Software Development :: Libraries :: Python Modules
Classifier: Topic :: Text Processing :: General
Requires-Python: >=3.8
License-File: LICENSE
Requires-Dist: anthropic
Requires-Dist: rich
Requires-Dist: typer[all]
